jupyter_translate.py
jupyter_translate-2025.1.1.dist-info/LICENSE
jupyter_translate-2025.1.1.dist-info/METADATA
jupyter_translate-2025.1.1.dist-info/WHEEL
jupyter_translate-2025.1.1.dist-info/entry_points.txt
jupyter_translate-2025.1.1.dist-info/top_level.txt
jupyter_translate-2025.1.1.dist-info/RECORD
