Metadata-Version: 2.2
Name: jupyter-translate
Version: 2025.1.1
Summary: A Python script for translating Jupyter notebook files.
Home-page: https://github.com/WittmannF/jupyter-translate
Author: Fernando Marcos Wittmann & Andre Belem
License: MIT
Classifier: Programming Language :: Python :: 3
Classifier: License :: OSI Approved :: MIT License
Classifier: Operating System :: OS Independent
Requires-Python: >=3.7
License-File: LICENSE
Requires-Dist: fire
Requires-Dist: deep-translator
Requires-Dist: googletrans==3.1.0a0
Requires-Dist: tqdm
Requires-Dist: numpy
Requires-Dist: scipy
Requires-Dist: matplotlib
Requires-Dist: pytest>=7.0.0
Requires-Dist: pytest-cov>=2.12.0
Provides-Extra: dev
Requires-Dist: pytest>=7.0.0; extra == "dev"
Requires-Dist: pytest-cov>=2.12.0; extra == "dev"
Dynamic: author
Dynamic: classifier
Dynamic: description
Dynamic: description-content-type
Dynamic: home-page
Dynamic: requires-dist
Dynamic: requires-python
Dynamic: summary
